odoo8_addon_purchase_requisition_type-8.0.1.0.0.99.dev15-py2.7-nspkg.pth
odoo8_addon_purchase_requisition_type-8.0.1.0.0.99.dev15.dist-info/DESCRIPTION.rst
odoo8_addon_purchase_requisition_type-8.0.1.0.0.99.dev15.dist-info/METADATA
odoo8_addon_purchase_requisition_type-8.0.1.0.0.99.dev15.dist-info/RECORD
odoo8_addon_purchase_requisition_type-8.0.1.0.0.99.dev15.dist-info/WHEEL
odoo8_addon_purchase_requisition_type-8.0.1.0.0.99.dev15.dist-info/metadata.json
odoo8_addon_purchase_requisition_type-8.0.1.0.0.99.dev15.dist-info/namespace_packages.txt
odoo8_addon_purchase_requisition_type-8.0.1.0.0.99.dev15.dist-info/top_level.txt
odoo_addons/purchase_requisition_type/README.rst
odoo_addons/purchase_requisition_type/__init__.py
odoo_addons/purchase_requisition_type/__openerp__.py
odoo_addons/purchase_requisition_type/i18n/ar.po
odoo_addons/purchase_requisition_type/i18n/bg.po
odoo_addons/purchase_requisition_type/i18n/bs.po
odoo_addons/purchase_requisition_type/i18n/ca.po
odoo_addons/purchase_requisition_type/i18n/ca_ES.po
odoo_addons/purchase_requisition_type/i18n/cs.po
odoo_addons/purchase_requisition_type/i18n/da.po
odoo_addons/purchase_requisition_type/i18n/de.po
odoo_addons/purchase_requisition_type/i18n/en_GB.po
odoo_addons/purchase_requisition_type/i18n/es.po
odoo_addons/purchase_requisition_type/i18n/es_AR.po
odoo_addons/purchase_requisition_type/i18n/es_CO.po
odoo_addons/purchase_requisition_type/i18n/es_CR.po
odoo_addons/purchase_requisition_type/i18n/es_EC.po
odoo_addons/purchase_requisition_type/i18n/es_ES.po
odoo_addons/purchase_requisition_type/i18n/es_MX.po
odoo_addons/purchase_requisition_type/i18n/es_PE.po
odoo_addons/purchase_requisition_type/i18n/es_VE.po
odoo_addons/purchase_requisition_type/i18n/eu.po
odoo_addons/purchase_requisition_type/i18n/fa.po
odoo_addons/purchase_requisition_type/i18n/fi.po
odoo_addons/purchase_requisition_type/i18n/fr.po
odoo_addons/purchase_requisition_type/i18n/gl.po
odoo_addons/purchase_requisition_type/i18n/he.po
odoo_addons/purchase_requisition_type/i18n/hr.po
odoo_addons/purchase_requisition_type/i18n/it.po
odoo_addons/purchase_requisition_type/i18n/ja.po
odoo_addons/purchase_requisition_type/i18n/lt.po
odoo_addons/purchase_requisition_type/i18n/lv.po
odoo_addons/purchase_requisition_type/i18n/mk.po
odoo_addons/purchase_requisition_type/i18n/mn.po
odoo_addons/purchase_requisition_type/i18n/nb.po
odoo_addons/purchase_requisition_type/i18n/nl.po
odoo_addons/purchase_requisition_type/i18n/nl_BE.po
